Metadata-Version: 2.1
Name: LUX2EV
Version: 2023.12.23.2
Summary: A very easy-to-use small software that uses the lux value measured by the illuminance meter to calculate the shutter speed under different ISO and aperture, and assist photography.
Home-page: https://github.com/EasyCam/LUX2EV/
Author: EasyCam
Author-email: hopephoto@outlook.com
License-File: LICENSE
Requires-Dist: PyQt6
